pegacorn/__init__.py
pegacorn/main.py
pegacorn/command/__init__.py
pegacorn/core/__init__.py
pegacorn-0.0.1.dist-info/LICENSE
pegacorn-0.0.1.dist-info/METADATA
pegacorn-0.0.1.dist-info/WHEEL
pegacorn-0.0.1.dist-info/top_level.txt
pegacorn-0.0.1.dist-info/RECORD
