Metadata-Version: 2.1
Name: pegacorn
Version: 0.0.1
Summary: pegacorn
Home-page: https://github.com/pegacorn-engine/pegacorn
Author: 0xonk
Author-email: 0xonkfd@gmail.com
Classifier: Programming Language :: Python :: 3
Classifier: License :: OSI Approved :: GNU General Public License v3 (GPLv3)
Classifier: Operating System :: OS Independent
Classifier: Topic :: Security
Requires-Python: >=3.10
License-File: LICENSE
Requires-Dist: androguard (==3.4.0a1)
Requires-Dist: click
